deri_log/__init__.py
deri_log/say_hello.py
jin_test_packet-0.0.1.dist-info/LICENSE
jin_test_packet-0.0.1.dist-info/METADATA
jin_test_packet-0.0.1.dist-info/WHEEL
jin_test_packet-0.0.1.dist-info/top_level.txt
jin_test_packet-0.0.1.dist-info/RECORD
