Metadata-Version: 2.1
Name: jin-test-packet
Version: 0.0.1
Summary: 这是我的第一个资源包，仅仅是测试如何制作资源包并上传PYPI
Home-page: UNKNOWN
Author: Jack_jin
Author-email: 2960688709@qq.com
License: UNKNOWN
Platform: UNKNOWN
Classifier: Programming Language :: Python :: 3
Classifier: License :: OSI Approved :: MIT License
Classifier: Operating System :: OS Independent
License-File: LICENSE
